_quay_version.py
omero_quay/__init__.py
omero_quay/py.typed
omero_quay/_compat/__init__.py
omero_quay/_compat/typing.py
omero_quay/clients/__init__.py
omero_quay/clients/excel.py
omero_quay/clients/http.py
omero_quay/core/__init__.py
omero_quay/core/config.py
omero_quay/core/connect.py
omero_quay/core/generator.py
omero_quay/core/http_handler.py
omero_quay/core/interface.py
omero_quay/core/manifest.py
omero_quay/core/provenance.py
omero_quay/core/quay.yml
omero_quay/core/utils.py
omero_quay/core/workers.py
omero_quay/icons/assay.svg
omero_quay/icons/directory.svg
omero_quay/icons/investigation.svg
omero_quay/icons/study.svg
omero_quay/managers/__init__.py
omero_quay/managers/filesystem.py
omero_quay/managers/irods.py
omero_quay/managers/manager.py
omero_quay/managers/omero.py
omero_quay/managers/rocrate.py
omero_quay/mdp/__init__.py
omero_quay/mdp/client.py
omero_quay/mdp/scheduler.py
omero_quay/mdp/worker.py
omero_quay/parsers/__init__.py
omero_quay/parsers/errors.py
omero_quay/parsers/excel.py
omero_quay/parsers/filesystem.py
omero_quay/parsers/validate_excel.py
omero_quay/parsers/validate_manifest.py
omero_quay/rocrate/__init__.py
omero_quay/rocrate/vignette_generator.py
omero_quay/schema/__init__.py
omero_quay/schema/example.yml
omero_quay/schema/manifest-schema.yml
omero_quay/static/html-tree-view.css
omero_quay/templates/annotation.json.j2
omero_quay/templates/assay.json.j2
omero_quay/templates/attribute.py.jinja
omero_quay/templates/collection.json.j2
omero_quay/templates/html-tree-view.html.j2
omero_quay/templates/html_browser_page_template.j2
omero_quay/templates/image.json.j2
omero_quay/templates/investigation.json.j2
omero_quay/templates/ro-crate-metadata.json.j2
omero_quay/templates/ro-crate-preview.html.j2
omero_quay/templates/study.json.j2
omero_quay/users/__init__.py
omero_quay/users/authentik.py
omero_quay/users/clerk.py
omero_quay/users/crud_user.py
omero_quay/users/irods.py
omero_quay/users/ldap.py
omero_quay/users/omero.py
omero_quay-1.2.0.dist-info/METADATA
omero_quay-1.2.0.dist-info/WHEEL
omero_quay-1.2.0.dist-info/licenses/LICENSE
omero_quay-1.2.0.dist-info/RECORD
