Metadata-Version: 2.4
Name: omero_quay
Version: 1.2.0
Summary: Omero Data Import Export Queue
Project-URL: Homepage, https://gitlab.in2p3.fr/fbi-data/omero-quay
Project-URL: Bug Tracker, https://gitlab.in2p3.fr/fbi-data/omero-quay/issues
Project-URL: Discussions, https://gitlab.in2p3.fr/fbi-data/omero-quay/discussions
Project-URL: Changelog, https://gitlab.in2p3.fr/fbi-data/omero-quay/releases
Author-email: Guillaume Gay <guillaume.gay@france-bioimaging.org>
License-Expression: MPL-2.0
License-File: LICENSE
Classifier: Development Status :: 1 - Planning
Classifier: Intended Audience :: Developers
Classifier: Intended Audience :: Science/Research
Classifier: Operating System :: OS Independent
Classifier: Programming Language :: Python
Classifier: Programming Language :: Python :: 3
Classifier: Programming Language :: Python :: 3 :: Only
Classifier: Programming Language :: Python :: 3.10
Classifier: Programming Language :: Python :: 3.11
Classifier: Programming Language :: Python :: 3.12
Classifier: Topic :: Scientific/Engineering
Classifier: Typing :: Typed
Requires-Python: <3.13,>=3.10
Requires-Dist: aicsimageio
Requires-Dist: ezomero==3.1.1
Requires-Dist: ffmpeg
Requires-Dist: imageio
Requires-Dist: jinja2
Requires-Dist: linkml-runtime
Requires-Dist: omero-cli-transfer
Requires-Dist: omero-py
Requires-Dist: openpyxl
Requires-Dist: pandas
Requires-Dist: pillow
Requires-Dist: pyarrow
Requires-Dist: python-irodsclient
Requires-Dist: requests
Requires-Dist: roc-validator
Requires-Dist: scikit-image
Requires-Dist: xsdata
Provides-Extra: dev
Requires-Dist: ezomero; extra == 'dev'
Requires-Dist: linkml; extra == 'dev'
Requires-Dist: mkdocs; extra == 'dev'
Requires-Dist: mkdocstrings[python]; extra == 'dev'
Requires-Dist: motor; extra == 'dev'
Requires-Dist: pre-commit; extra == 'dev'
Requires-Dist: pymongo; extra == 'dev'
Requires-Dist: pytest; extra == 'dev'
Requires-Dist: pytest-asyncio; extra == 'dev'
Requires-Dist: pytest-cov; extra == 'dev'
Requires-Dist: pyzmq; extra == 'dev'
Requires-Dist: tornado; extra == 'dev'
Requires-Dist: zeroc-ice==3.6.5; extra == 'dev'
Provides-Extra: server
Requires-Dist: ezomero; extra == 'server'
Requires-Dist: motor; extra == 'server'
Requires-Dist: pymongo; extra == 'server'
Requires-Dist: pyzmq; extra == 'server'
Requires-Dist: tornado; extra == 'server'
Requires-Dist: zeroc-ice==3.6.5; extra == 'server'
